airavata_mft_cli/__init__.py
airavata_mft_cli/base.py
airavata_mft_cli/bootstrap.py
airavata_mft_cli/config.py
airavata_mft_cli/main.py
airavata_mft_cli/operations.py
airavata_mft_cli/storage/__init__.py
airavata_mft_cli/storage/azure.py
airavata_mft_cli/storage/gcs.py
airavata_mft_cli/storage/http.py
airavata_mft_cli/storage/local.py
airavata_mft_cli/storage/s3.py
airavata_mft_cli/storage/scp.py
airavata_mft_cli/storage/swift.py
airavata_mft_cli/util.py
airavata_mft_cli-0.1.24.dist-info/METADATA
airavata_mft_cli-0.1.24.dist-info/WHEEL
airavata_mft_cli-0.1.24.dist-info/entry_points.txt
airavata_mft_cli-0.1.24.dist-info/RECORD
