Metadata-Version: 2.1
Name: airavata-mft-cli
Version: 0.1.24
Summary: Command Line Client for Apache Airavata MFT data transfer software
Home-page: https://github.com/apache/airavata-mft
License: Apache-2.0
Keywords: MFT,Data,High Thorught Data Transfer,Multi Protocol,S3,GCS,Azure,SCP,Google Drive,Swift,Box,DropBox
Author: Dimuthu Wannipurage
Author-email: dwannipu@iu.edu
Maintainer: Apache Airavata Developers
Maintainer-email: dev@apache.airavata.org
Requires-Python: >=3.10,<4.0
Classifier: License :: OSI Approved :: Apache Software License
Classifier: Programming Language :: Python :: 3
Classifier: Programming Language :: Python :: 3.10
Classifier: Programming Language :: Python :: 3.11
Requires-Dist: airavata-mft-sdk (==0.0.1a34)
Requires-Dist: grpcio (==1.46.3) ; platform_machine != "arm64" and python_version < "3.11"
Requires-Dist: grpcio (==1.47.0rc1) ; platform_machine == "arm64" and python_version < "3.11"
Requires-Dist: grpcio (==1.60.0) ; platform_machine != "arm64" and python_version >= "3.11"
Requires-Dist: grpcio (==1.60.0) ; platform_machine == "arm64" and python_version >= "3.11"
Requires-Dist: grpcio-tools (==1.46.3) ; platform_machine != "arm64" and python_version < "3.11"
Requires-Dist: grpcio-tools (==1.47.0rc1) ; platform_machine == "arm64" and python_version < "3.11"
Requires-Dist: grpcio-tools (==1.60.0) ; platform_machine != "arm64" and python_version >= "3.11"
Requires-Dist: grpcio-tools (==1.60.0) ; platform_machine == "arm64" and python_version >= "3.11"
Requires-Dist: pandas (>=2.0.3,<3.0.0)
Requires-Dist: pick (==2.2.0)
Requires-Dist: typer[all] (>=0.7.0,<0.8.0)
